zigpy_espzb/__init__.py
zigpy_espzb/api.py
zigpy_espzb/exception.py
zigpy_espzb/types.py
zigpy_espzb/uart.py
zigpy_espzb/zigbee/__init__.py
zigpy_espzb/zigbee/application.py
zigpy_espzb-0.0.1.dist-info/COPYING
zigpy_espzb-0.0.1.dist-info/LICENSE
zigpy_espzb-0.0.1.dist-info/METADATA
zigpy_espzb-0.0.1.dist-info/WHEEL
zigpy_espzb-0.0.1.dist-info/top_level.txt
zigpy_espzb-0.0.1.dist-info/RECORD
