Metadata-Version: 2.1
Name: zigpy-espzb
Version: 0.0.1
Summary: A library which communicates with Espressif radios for zigpy
Author-email: Liu Han <liuhan@espressif.com>
License: GPL-3.0
Project-URL: repository, https://github.com/lhespress/zigpy-espzb
Requires-Python: >=3.8
License-File: LICENSE
License-File: COPYING
Requires-Dist: voluptuous
Requires-Dist: zigpy >=0.60.2
Requires-Dist: async-timeout ; python_version < "3.11"
Provides-Extra: testing
Requires-Dist: pytest >=7.1.2 ; extra == 'testing'
Requires-Dist: pytest-asyncio >=0.19.0 ; extra == 'testing'
Requires-Dist: pytest-timeout >=2.1.0 ; extra == 'testing'
Requires-Dist: pytest-mock >=3.8.2 ; extra == 'testing'
Requires-Dist: pytest-cov >=3.0.0 ; extra == 'testing'
